dotsCLI/__init__.py
dotsCLI/config/__init__.py
dotsCLI/config/settings.py
dotsCLI/docker/__init__.py
dotsCLI/docker/parser.py
dotsCLI/dts.py
dotsCLI/samples/config
dotsCLI/samples/docker-compose.yml
dotscli-0.1.0.dist-info/entry_points.txt
dotscli-0.1.0.dist-info/WHEEL
dotscli-0.1.0.dist-info/METADATA
dotscli-0.1.0.dist-info/RECORD
