Metadata-Version: 2.1
Name: dotscli
Version: 0.1.0
Summary: A command line interface for automating containerization
Author: Yathartha Goenka
Author-email: goenkayathartha2002@gmail.com
Requires-Python: >=3.8,<4.0
Classifier: Programming Language :: Python :: 3
Classifier: Programming Language :: Python :: 3.8
Classifier: Programming Language :: Python :: 3.9
Classifier: Programming Language :: Python :: 3.10
Requires-Dist: PyYAML (>=6.0,<7.0)
Requires-Dist: click (>=8.1.4,<9.0.0)
Requires-Dist: paramiko (>=3.2.0,<4.0.0)
